README.md
setup.py
xlsxr/__init__.py
xlsxr/exceptions.py
xlsxr/namespaces.py
xlsxr/sheet.py
xlsxr/style.py
xlsxr/util.py
xlsxr/workbook.py
xlsxr.egg-info/PKG-INFO
xlsxr.egg-info/SOURCES.txt
xlsxr.egg-info/dependency_links.txt
xlsxr.egg-info/requires.txt
xlsxr.egg-info/top_level.txt