Metadata-Version: 2.1
Name: xlsxr
Version: 0.1
Summary: Read very large Excel XLSX files efficiently
Home-page: UNKNOWN
Author: David Megginson
Author-email: megginson@un.org
License: UNKNOWN
Platform: UNKNOWN
